numpygraph/__init__.py
numpygraph/graph/__init__.py
numpygraph/graph/sampler.py
numpygraph/importer/__init__.py
numpygraph/importer/importer.py
numpygraph/importer/importer_node.py
numpygraph/importer/parser.py
numpygraph/tools/__init__.py
numpygraph/tools/arraydict.py
numpygraph/tools/arraylist.py
numpygraph/tools/fileshutil.py
numpygraph/tools/tools.py
numpygraph-0.0.1.3.dist-info/.ipynb_checkpoints/PKG-INFO-checkpoint
numpygraph-0.0.1.3.dist-info/METADATA
numpygraph-0.0.1.3.dist-info/WHEEL
numpygraph-0.0.1.3.dist-info/top_level.txt
numpygraph-0.0.1.3.dist-info/RECORD
