Metadata-Version: 2.1
Name: numpygraph
Version: 0.0.1.3
Summary: A small example package
Home-page: https://github.com/hp027/numpygraph
Author: hp027
Author-email: hp027@foxmail.com
License: UNKNOWN
Platform: UNKNOWN
Classifier: Programming Language :: Python :: 3
Classifier: License :: OSI Approved :: MIT License
Classifier: Operating System :: OS Independent
Requires-Python: >=3.6
Requires-Dist: rich
